aots/__init__.py
aots-0.0.1.dist-info/METADATA
aots-0.0.1.dist-info/RECORD
aots-0.0.1.dist-info/WHEEL
aots-0.0.1.dist-info/top_level.txt
